ayano/__init__.py
ayano/exceptions/__init__.py
ayano/exceptions/filters.py
ayano/filters/__init__.py
ayano/filters/commands/__init__.py
ayano/filters/commands/start.py
ayano/middlewares/__init__.py
ayano/middlewares/throttling.py
ayano/middlewares/valistaions/__init__.py
ayano/middlewares/valistaions/channel.py
ayano/middlewares/valistaions/chat_type.py
ayano/middlewares/valistaions/compare_model_attrs.py
ayano/patterns/__init__.py
ayano/patterns/in_private.py
ayano/patterns/is_block.py
ayano/src/__init__.py
ayano/src/pagination/__init__.py
ayano/src/pagination/callbacks.py
ayano/src/pagination/keyboards.py
ayano/src/pagination/pagination.py
ayano/utils/__init__.py
ayano/utils/validation.py
ayano-0.2.0.dist-info/LICENSE
ayano-0.2.0.dist-info/METADATA
ayano-0.2.0.dist-info/WHEEL
ayano-0.2.0.dist-info/top_level.txt
ayano-0.2.0.dist-info/RECORD
